awslogs/__init__.py
awslogs/_version.py
awslogs/bin.py
awslogs/core.py
awslogs/exceptions.py
awslogs_oguzzi-0.12.2.dist-info/AUTHORS
awslogs_oguzzi-0.12.2.dist-info/COPYING
awslogs_oguzzi-0.12.2.dist-info/METADATA
awslogs_oguzzi-0.12.2.dist-info/WHEEL
awslogs_oguzzi-0.12.2.dist-info/entry_points.txt
awslogs_oguzzi-0.12.2.dist-info/top_level.txt
awslogs_oguzzi-0.12.2.dist-info/RECORD
