Metadata-Version: 2.1
Name: awslogs-oguzzi
Version: 0.12.2
Summary: awslogs is a simple command line tool to read aws cloudwatch logs.
Home-page: https://github.com/olivierguzzi/awslogs
Author: Olivier Guzzi
Author-email: oguzzi@shopstyle.com
License: BSD
Keywords: aws logs cloudwatch
Platform: any
Classifier: Programming Language :: Python :: 3
Classifier: Programming Language :: Python :: 2
Classifier: Development Status :: 4 - Beta
Classifier: Environment :: Web Environment
Classifier: Intended Audience :: Developers
Classifier: License :: OSI Approved :: BSD License
Classifier: Operating System :: OS Independent
Classifier: Topic :: Utilities
Requires-Dist: boto3 (>=1.5.0)
Requires-Dist: jmespath (<1.0.0,>=0.7.1)
Requires-Dist: termcolor (>=1.1.0)
Requires-Dist: python-dateutil (>=2.4.0)
Requires-Dist: argparse (>=1.1.0) ; python_version in "2.4, 2.5, 2.6"
